LICENSE
README.md
setup.cfg
setup.py
pyparsec.egg-info/PKG-INFO
pyparsec.egg-info/SOURCES.txt
pyparsec.egg-info/dependency_links.txt
pyparsec.egg-info/top_level.txt
src/parsec/__init__.py
src/parsec/atom.py
src/parsec/builtin.py
src/parsec/combinator.py
src/parsec/error.py
src/parsec/parsec.py
src/parsec/result.py
src/parsec/state.py
src/parsec/text.py
src/parsec/utils.py
src/tests/__init__.py
src/tests/atom.py
src/tests/combinator.py
src/tests/lr.py
src/tests/state.py
src/tests/text.py
src/tests/utils.py