Metadata-Version: 2.1
Name: pyparsec
Version: 0.8.6
Summary: Parsec From Haskell Python 3 Portable
Home-page: https://github.com/Dwarfartisan/pyparsec
Author: marsliu
Author-email: mars.liu@outlook.com
License: MIT
Classifier: Topic :: Utilities
Classifier: Programming Language :: Python :: 3.5
Classifier: Programming Language :: Python :: 3.6
Classifier: Programming Language :: Python :: 3.7
Classifier: Programming Language :: Python :: 3.8
Classifier: Programming Language :: Python :: 3.9
Classifier: Programming Language :: Python :: 3 :: Only
Classifier: License :: OSI Approved :: MIT License
License-File: LICENSE
